pywis_topics/__init__.py
pywis_topics/bundle.py
pywis_topics/centre_id.py
pywis_topics/pygeoapi_plugin.py
pywis_topics/topics.py
pywis_topics/util.py
pywis_topics-0.3.6.dist-info/licenses/LICENSE
pywis_topics-0.3.6.dist-info/METADATA
pywis_topics-0.3.6.dist-info/WHEEL
pywis_topics-0.3.6.dist-info/entry_points.txt
pywis_topics-0.3.6.dist-info/top_level.txt
pywis_topics-0.3.6.dist-info/RECORD
