Metadata-Version: 2.4
Name: pywis-topics
Version: 0.3.6
Summary: pywis-topics is a utility to work with the WIS2 Topic Hierarchy
Home-page: https://github.com/World-Meteorological-Organization/pywis-topics
Author: Tom Kralidis
Author-email: tomkralidis@gmail.com
Maintainer: Tom Kralidis
Maintainer-email: tomkraldis@gmail.com
License: Apache Software License
Keywords: WIS2 WTH topics
Platform: all
Classifier: Development Status :: 4 - Beta
Classifier: Environment :: Console
Classifier: Intended Audience :: Developers
Classifier: Intended Audience :: Science/Research
Classifier: License :: OSI Approved :: Apache Software License
Classifier: Operating System :: OS Independent
Classifier: Programming Language :: Python
License-File: LICENSE
Requires-Dist: click
Dynamic: author
Dynamic: author-email
Dynamic: classifier
Dynamic: description
Dynamic: description-content-type
Dynamic: home-page
Dynamic: keywords
Dynamic: license
Dynamic: license-file
Dynamic: maintainer
Dynamic: maintainer-email
Dynamic: platform
Dynamic: requires-dist
Dynamic: summary
